setup.py
ovos_wake_word_plugin_pocketsphinx/__init__.py
ovos_wake_word_plugin_pocketsphinx.egg-info/PKG-INFO
ovos_wake_word_plugin_pocketsphinx.egg-info/SOURCES.txt
ovos_wake_word_plugin_pocketsphinx.egg-info/dependency_links.txt
ovos_wake_word_plugin_pocketsphinx.egg-info/entry_points.txt
ovos_wake_word_plugin_pocketsphinx.egg-info/requires.txt
ovos_wake_word_plugin_pocketsphinx.egg-info/top_level.txt
ovos_wake_word_plugin_pocketsphinx.egg-info/zip-safe